README.rst
setup.cfg
setup.py
monica/__init__.py
monica/config.py
monica/monica.py
monica.egg-info/PKG-INFO
monica.egg-info/SOURCES.txt
monica.egg-info/dependency_links.txt
monica.egg-info/entry_points.txt
monica.egg-info/requires.txt
monica.egg-info/top_level.txt