Metadata-Version: 1.0
Name: monica
Version: 0.0.9
Summary: monica is a command line chef that brings you tasty food
Home-page: https://github.com/zephrys/monica
Author: Zephrys
Author-email: anomaly.the@gmail.com
License: MIT
Keywords: license,food,monica,command line,cli,zomato
Platform: UNKNOWN
